{
  "dashboardFilters": [],
  "displayName": "Blockchain Node Engine dashboard",
  "labels": {},
  "mosaicLayout": {
    "columns": 12,
    "tiles": [
      {
        "height": 4,
        "widget": {
          "title": "Peer Count",
          "xyChart": {
            "chartOptions": {
              "mode": "COLOR"
            },
            "dataSets": [
              {
                "minAlignmentPeriod": "60s",
                "plotType": "LINE",
                "targetAxis": "Y1",
                "timeSeriesQuery": {
                  "timeSeriesFilter": {
                    "aggregation": {
                      "alignmentPeriod": "60s",
                      "crossSeriesReducer": "REDUCE_MEAN",
                      "groupByFields": [
                        "resource.label.\"blockchain_node_id\""
                      ],
                      "perSeriesAligner": "ALIGN_MEAN"
                    },
                    "filter": "metric.type=\"blockchainnodeengine.googleapis.com/node/active_peers\" resource.type=\"blockchainnodeengine.googleapis.com/BlockchainNode\""
                  }
                }
              }
            ],
            "thresholds": [],
            "timeshiftDuration": "0s",
            "yAxis": {
              "label": "",
              "scale": "LINEAR"
            }
          }
        },
        "width": 6
      },
      {
        "height": 4,
        "widget": {
          "title": "Pending Transactions",
          "xyChart": {
            "chartOptions": {
              "mode": "COLOR"
            },
            "dataSets": [
              {
                "minAlignmentPeriod": "60s",
                "plotType": "LINE",
                "targetAxis": "Y1",
                "timeSeriesQuery": {
                  "timeSeriesFilter": {
                    "aggregation": {
                      "alignmentPeriod": "60s",
                      "crossSeriesReducer": "REDUCE_MEAN",
                      "groupByFields": [
                        "resource.label.\"blockchain_node_id\""
                      ],
                      "perSeriesAligner": "ALIGN_MEAN"
                    },
                    "filter": "metric.type=\"blockchainnodeengine.googleapis.com/node/pending_transactions\" resource.type=\"blockchainnodeengine.googleapis.com/BlockchainNode\""
                  }
                }
              }
            ],
            "thresholds": [],
            "timeshiftDuration": "0s",
            "yAxis": {
              "label": "",
              "scale": "LINEAR"
            }
          }
        },
        "width": 6,
        "xPos": 6
      },
      {
        "height": 4,
        "widget": {
          "title": "Request Count",
          "xyChart": {
            "chartOptions": {
              "mode": "COLOR"
            },
            "dataSets": [
              {
                "minAlignmentPeriod": "60s",
                "plotType": "LINE",
                "targetAxis": "Y1",
                "timeSeriesQuery": {
                  "timeSeriesFilter": {
                    "aggregation": {
                      "alignmentPeriod": "60s",
                      "perSeriesAligner": "ALIGN_RATE"
                    },
                    "filter": "metric.type=\"blockchainnodeengine.googleapis.com/node/total_request_count\" resource.type=\"blockchainnodeengine.googleapis.com/BlockchainNode\"",
                    "secondaryAggregation": {
                      "alignmentPeriod": "60s",
                      "crossSeriesReducer": "REDUCE_MEAN",
                      "groupByFields": [
                        "resource.label.\"blockchain_node_id\""
                      ],
                      "perSeriesAligner": "ALIGN_MEAN"
                    }
                  }
                }
              }
            ],
            "thresholds": [],
            "timeshiftDuration": "0s",
            "yAxis": {
              "label": "",
              "scale": "LINEAR"
            }
          }
        },
        "width": 6,
        "xPos": 6,
        "yPos": 4
      },
      {
        "height": 4,
        "widget": {
          "title": "Memory Utilization",
          "xyChart": {
            "chartOptions": {
              "mode": "COLOR"
            },
            "dataSets": [
              {
                "minAlignmentPeriod": "60s",
                "plotType": "LINE",
                "targetAxis": "Y1",
                "timeSeriesQuery": {
                  "timeSeriesFilter": {
                    "aggregation": {
                      "alignmentPeriod": "60s",
                      "crossSeriesReducer": "REDUCE_MEAN",
                      "groupByFields": [
                        "resource.label.\"blockchain_node_id\""
                      ],
                      "perSeriesAligner": "ALIGN_MEAN"
                    },
                    "filter": "metric.type=\"blockchainnodeengine.googleapis.com/node/memory/utilization\" resource.type=\"blockchainnodeengine.googleapis.com/BlockchainNode\""
                  }
                }
              }
            ],
            "thresholds": [],
            "timeshiftDuration": "0s",
            "yAxis": {
              "label": "",
              "scale": "LINEAR"
            }
          }
        },
        "width": 6,
        "yPos": 8
      },
      {
        "height": 4,
        "widget": {
          "title": "CPU Utilization",
          "xyChart": {
            "chartOptions": {
              "mode": "COLOR"
            },
            "dataSets": [
              {
                "minAlignmentPeriod": "60s",
                "plotType": "LINE",
                "targetAxis": "Y1",
                "timeSeriesQuery": {
                  "timeSeriesFilter": {
                    "aggregation": {
                      "alignmentPeriod": "60s",
                      "crossSeriesReducer": "REDUCE_MEAN",
                      "groupByFields": [
                        "resource.label.\"blockchain_node_id\""
                      ],
                      "perSeriesAligner": "ALIGN_MEAN"
                    },
                    "filter": "metric.type=\"blockchainnodeengine.googleapis.com/node/cpu/utilization\" resource.type=\"blockchainnodeengine.googleapis.com/BlockchainNode\""
                  }
                }
              }
            ],
            "thresholds": [],
            "timeshiftDuration": "0s",
            "yAxis": {
              "label": "",
              "scale": "LINEAR"
            }
          }
        },
        "width": 6,
        "yPos": 4
      },
      {
        "height": 4,
        "widget": {
          "title": "Disk Operations",
          "xyChart": {
            "chartOptions": {
              "mode": "COLOR"
            },
            "dataSets": [
              {
                "minAlignmentPeriod": "60s",
                "plotType": "LINE",
                "targetAxis": "Y1",
                "timeSeriesQuery": {
                  "timeSeriesFilter": {
                    "aggregation": {
                      "alignmentPeriod": "60s",
                      "perSeriesAligner": "ALIGN_RATE"
                    },
                    "filter": "metric.type=\"blockchainnodeengine.googleapis.com/node/disk/total_ops_count\" resource.type=\"blockchainnodeengine.googleapis.com/BlockchainNode\"",
                    "secondaryAggregation": {
                      "alignmentPeriod": "60s",
                      "crossSeriesReducer": "REDUCE_MEAN",
                      "groupByFields": [
                        "metric.label.\"direction\"",
                        "resource.label.\"blockchain_node_id\""
                      ],
                      "perSeriesAligner": "ALIGN_MEAN"
                    }
                  }
                }
              }
            ],
            "thresholds": [],
            "timeshiftDuration": "0s",
            "yAxis": {
              "label": "",
              "scale": "LINEAR"
            }
          }
        },
        "width": 6,
        "xPos": 6,
        "yPos": 8
      }
    ]
  }
}
