{
  "category": "CUSTOM",
  "displayName": "Apache Flink Task Manager Prometheus Overview",
  "mosaicLayout": {
    "columns": 12,
    "tiles": [
      {
        "height": 4,
        "widget": {
          "title": "CPU Load",
          "xyChart": {
            "chartOptions": {
              "mode": "COLOR"
            },
            "dataSets": [
              {
                "plotType": "LINE",
                "targetAxis": "Y1",
                "timeSeriesQuery": {
                  "prometheusQuery": "flink_taskmanager_Status_JVM_CPU_Load"
                }
              }
            ],
            "timeshiftDuration": "0s",
            "yAxis": {
              "label": "y1Axis",
              "scale": "LINEAR"
            }
          }
        },
        "width": 4,
        "xPos": 0,
        "yPos": 0
      },
      {
        "height": 4,
        "widget": {
          "title": "CPU Time",
          "xyChart": {
            "chartOptions": {
              "mode": "COLOR"
            },
            "dataSets": [
              {
                "plotType": "LINE",
                "targetAxis": "Y1",
                "timeSeriesQuery": {
                  "prometheusQuery": "flink_taskmanager_Status_JVM_CPU_Time"
                }
              }
            ],
            "timeshiftDuration": "0s",
            "yAxis": {
              "label": "y1Axis",
              "scale": "LINEAR"
            }
          }
        },
        "width": 4,
        "xPos": 4,
        "yPos": 0
      },
      {
        "height": 4,
        "widget": {
          "title": "Threads",
          "xyChart": {
            "chartOptions": {
              "mode": "COLOR"
            },
            "dataSets": [
              {
                "plotType": "LINE",
                "targetAxis": "Y1",
                "timeSeriesQuery": {
                  "prometheusQuery": "flink_taskmanager_Status_JVM_Threads_Count"
                }
              }
            ],
            "timeshiftDuration": "0s",
            "yAxis": {
              "label": "y1Axis",
              "scale": "LINEAR"
            }
          }
        },
        "width": 4,
        "xPos": 8,
        "yPos": 0
      },
      {
        "height": 4,
        "widget": {
          "title": "Heap Used (bytes)",
          "xyChart": {
            "chartOptions": {
              "mode": "COLOR"
            },
            "dataSets": [
              {
                "plotType": "LINE",
                "targetAxis": "Y1",
                "timeSeriesQuery": {
                  "prometheusQuery": "flink_taskmanager_Status_JVM_Memory_Heap_Used"
                }
              }
            ],
            "timeshiftDuration": "0s",
            "yAxis": {
              "label": "y1Axis",
              "scale": "LINEAR"
            }
          }
        },
        "width": 4,
        "xPos": 0,
        "yPos": 4
      },
      {
        "height": 4,
        "widget": {
          "title": "Heap Committed (bytes)",
          "xyChart": {
            "chartOptions": {
              "mode": "COLOR"
            },
            "dataSets": [
              {
                "plotType": "LINE",
                "targetAxis": "Y1",
                "timeSeriesQuery": {
                  "prometheusQuery": "flink_taskmanager_Status_JVM_Memory_Heap_Committed"
                }
              }
            ],
            "timeshiftDuration": "0s",
            "yAxis": {
              "label": "y1Axis",
              "scale": "LINEAR"
            }
          }
        },
        "width": 4,
        "xPos": 4,
        "yPos": 4
      },
      {
        "height": 4,
        "widget": {
          "title": "Heap Max (bytes)",
          "xyChart": {
            "chartOptions": {
              "mode": "COLOR"
            },
            "dataSets": [
              {
                "plotType": "LINE",
                "targetAxis": "Y1",
                "timeSeriesQuery": {
                  "prometheusQuery": "flink_taskmanager_Status_JVM_Memory_Heap_Max"
                }
              }
            ],
            "timeshiftDuration": "0s",
            "yAxis": {
              "label": "y1Axis",
              "scale": "LINEAR"
            }
          }
        },
        "width": 4,
        "xPos": 8,
        "yPos": 4
      },
      {
        "height": 4,
        "widget": {
          "title": "Nonheap Used (bytes)",
          "xyChart": {
            "chartOptions": {
              "mode": "COLOR"
            },
            "dataSets": [
              {
                "plotType": "LINE",
                "targetAxis": "Y1",
                "timeSeriesQuery": {
                  "prometheusQuery": "flink_taskmanager_Status_JVM_Memory_NonHeap_Used"
                }
              }
            ],
            "timeshiftDuration": "0s",
            "yAxis": {
              "label": "y1Axis",
              "scale": "LINEAR"
            }
          }
        },
        "width": 4,
        "xPos": 0,
        "yPos": 8
      },
      {
        "height": 4,
        "widget": {
          "title": "Nonheap Committed (bytes)",
          "xyChart": {
            "chartOptions": {
              "mode": "COLOR"
            },
            "dataSets": [
              {
                "plotType": "LINE",
                "targetAxis": "Y1",
                "timeSeriesQuery": {
                  "prometheusQuery": "flink_taskmanager_Status_JVM_Memory_NonHeap_Committed"
                }
              }
            ],
            "timeshiftDuration": "0s",
            "yAxis": {
              "label": "y1Axis",
              "scale": "LINEAR"
            }
          }
        },
        "width": 4,
        "xPos": 4,
        "yPos": 8
      },
      {
        "height": 4,
        "widget": {
          "title": "Nonheap Max (bytes)",
          "xyChart": {
            "chartOptions": {
              "mode": "COLOR"
            },
            "dataSets": [
              {
                "plotType": "LINE",
                "targetAxis": "Y1",
                "timeSeriesQuery": {
                  "prometheusQuery": "flink_taskmanager_Status_JVM_Memory_NonHeap_Max"
                }
              }
            ],
            "timeshiftDuration": "0s",
            "yAxis": {
              "label": "y1Axis",
              "scale": "LINEAR"
            }
          }
        },
        "width": 4,
        "xPos": 8,
        "yPos": 8
      },
      {
        "height": 4,
        "widget": {
          "title": "Metaspace Used (bytes)",
          "xyChart": {
            "chartOptions": {
              "mode": "COLOR"
            },
            "dataSets": [
              {
                "plotType": "LINE",
                "targetAxis": "Y1",
                "timeSeriesQuery": {
                  "prometheusQuery": "flink_taskmanager_Status_JVM_Memory_Metaspace_Used"
                }
              }
            ],
            "timeshiftDuration": "0s",
            "yAxis": {
              "label": "y1Axis",
              "scale": "LINEAR"
            }
          }
        },
        "width": 4,
        "xPos": 0,
        "yPos": 12
      },
      {
        "height": 4,
        "widget": {
          "title": "Metaspace Committed (bytes)",
          "xyChart": {
            "chartOptions": {
              "mode": "COLOR"
            },
            "dataSets": [
              {
                "plotType": "LINE",
                "targetAxis": "Y1",
                "timeSeriesQuery": {
                  "prometheusQuery": "flink_taskmanager_Status_JVM_Memory_Metaspace_Committed"
                }
              }
            ],
            "timeshiftDuration": "0s",
            "yAxis": {
              "label": "y1Axis",
              "scale": "LINEAR"
            }
          }
        },
        "width": 4,
        "xPos": 4,
        "yPos": 12
      },
      {
        "height": 4,
        "widget": {
          "title": "Metaspace Max (bytes)",
          "xyChart": {
            "chartOptions": {
              "mode": "COLOR"
            },
            "dataSets": [
              {
                "plotType": "LINE",
                "targetAxis": "Y1",
                "timeSeriesQuery": {
                  "prometheusQuery": "flink_taskmanager_Status_JVM_Memory_Metaspace_Max"
                }
              }
            ],
            "timeshiftDuration": "0s",
            "yAxis": {
              "label": "y1Axis",
              "scale": "LINEAR"
            }
          }
        },
        "width": 4,
        "xPos": 8,
        "yPos": 12
      },
      {
        "height": 4,
        "widget": {
          "title": "Direct Used (bytes)",
          "xyChart": {
            "chartOptions": {
              "mode": "COLOR"
            },
            "dataSets": [
              {
                "plotType": "LINE",
                "targetAxis": "Y1",
                "timeSeriesQuery": {
                  "prometheusQuery": "flink_taskmanager_Status_JVM_Memory_Direct_MemoryUsed"
                }
              }
            ],
            "timeshiftDuration": "0s",
            "yAxis": {
              "label": "y1Axis",
              "scale": "LINEAR"
            }
          }
        },
        "width": 6,
        "xPos": 0,
        "yPos": 16
      },
      {
        "height": 4,
        "widget": {
          "title": "Direct Total Capacity (bytes)",
          "xyChart": {
            "chartOptions": {
              "mode": "COLOR"
            },
            "dataSets": [
              {
                "plotType": "LINE",
                "targetAxis": "Y1",
                "timeSeriesQuery": {
                  "prometheusQuery": "flink_taskmanager_Status_JVM_Memory_Direct_TotalCapacity"
                }
              }
            ],
            "timeshiftDuration": "0s",
            "yAxis": {
              "label": "y1Axis",
              "scale": "LINEAR"
            }
          }
        },
        "width": 6,
        "xPos": 6,
        "yPos": 16
      },
      {
        "height": 4,
        "widget": {
          "title": "Mapped Used (bytes)",
          "xyChart": {
            "chartOptions": {
              "mode": "COLOR"
            },
            "dataSets": [
              {
                "plotType": "LINE",
                "targetAxis": "Y1",
                "timeSeriesQuery": {
                  "prometheusQuery": "flink_taskmanager_Status_JVM_Memory_Mapped_MemoryUsed"
                }
              }
            ],
            "timeshiftDuration": "0s",
            "yAxis": {
              "label": "y1Axis",
              "scale": "LINEAR"
            }
          }
        },
        "width": 6,
        "xPos": 0,
        "yPos": 20
      },
      {
        "height": 4,
        "widget": {
          "title": "Mapped Total Capacity (bytes)",
          "xyChart": {
            "chartOptions": {
              "mode": "COLOR"
            },
            "dataSets": [
              {
                "plotType": "LINE",
                "targetAxis": "Y1",
                "timeSeriesQuery": {
                  "prometheusQuery": "flink_taskmanager_Status_JVM_Memory_Mapped_TotalCapacity"
                }
              }
            ],
            "timeshiftDuration": "0s",
            "yAxis": {
              "label": "y1Axis",
              "scale": "LINEAR"
            }
          }
        },
        "width": 6,
        "xPos": 6,
        "yPos": 20
      },
      {
        "height": 4,
        "widget": {
          "title": "Garbage Collector Time",
          "xyChart": {
            "chartOptions": {
              "mode": "COLOR"
            },
            "dataSets": [
              {
                "plotType": "LINE",
                "targetAxis": "Y1",
                "timeSeriesQuery": {
                  "prometheusQuery": "flink_taskmanager_Status_JVM_GarbageCollector_G1_Old_Generation_Time"
                }
              },
              {
                "plotType": "LINE",
                "targetAxis": "Y1",
                "timeSeriesQuery": {
                  "prometheusQuery": "flink_taskmanager_Status_JVM_GarbageCollector_G1_Young_Generation_Time"
                }
              }
            ],
            "timeshiftDuration": "0s",
            "yAxis": {
              "label": "y1Axis",
              "scale": "LINEAR"
            }
          }
        },
        "width": 6,
        "xPos": 0,
        "yPos": 24
      },
      {
        "height": 4,
        "widget": {
          "title": "Garbage Collector Count",
          "xyChart": {
            "chartOptions": {
              "mode": "COLOR"
            },
            "dataSets": [
              {
                "plotType": "LINE",
                "targetAxis": "Y1",
                "timeSeriesQuery": {
                  "prometheusQuery": "flink_taskmanager_Status_JVM_GarbageCollector_G1_Old_Generation_Count"
                }
              },
              {
                "plotType": "LINE",
                "targetAxis": "Y1",
                "timeSeriesQuery": {
                  "prometheusQuery": "flink_taskmanager_Status_JVM_GarbageCollector_G1_Young_Generation_Count"
                }
              }
            ],
            "timeshiftDuration": "0s",
            "yAxis": {
              "label": "y1Axis",
              "scale": "LINEAR"
            }
          }
        },
        "width": 6,
        "xPos": 6,
        "yPos": 24
      },
      {
        "height": 4,
        "widget": {
          "title": "Managed Memory Used",
          "xyChart": {
            "chartOptions": {
              "mode": "COLOR"
            },
            "dataSets": [
              {
                "plotType": "LINE",
                "targetAxis": "Y1",
                "timeSeriesQuery": {
                  "prometheusQuery": "flink_taskmanager_Status_Flink_Memory_Managed_Used"
                }
              }
            ],
            "timeshiftDuration": "0s",
            "yAxis": {
              "label": "y1Axis",
              "scale": "LINEAR"
            }
          }
        },
        "width": 4,
        "xPos": 0,
        "yPos": 28
      },
      {
        "height": 4,
        "widget": {
          "title": "Managed Memory Total",
          "xyChart": {
            "chartOptions": {
              "mode": "COLOR"
            },
            "dataSets": [
              {
                "plotType": "LINE",
                "targetAxis": "Y1",
                "timeSeriesQuery": {
                  "prometheusQuery": "flink_taskmanager_Status_Flink_Memory_Managed_Total"
                }
              }
            ],
            "timeshiftDuration": "0s",
            "yAxis": {
              "label": "y1Axis",
              "scale": "LINEAR"
            }
          }
        },
        "width": 4,
        "xPos": 4,
        "yPos": 28
      },
      {
        "height": 4,
        "widget": {
          "title": "Class Loader",
          "xyChart": {
            "chartOptions": {
              "mode": "COLOR"
            },
            "dataSets": [
              {
                "plotType": "LINE",
                "targetAxis": "Y1",
                "timeSeriesQuery": {
                  "prometheusQuery": "flink_taskmanager_Status_JVM_ClassLoader_ClassesLoaded"
                }
              },
              {
                "plotType": "LINE",
                "targetAxis": "Y1",
                "timeSeriesQuery": {
                  "prometheusQuery": "flink_taskmanager_Status_JVM_ClassLoader_ClassesUnloaded"
                }
              }
            ],
            "timeshiftDuration": "0s",
            "yAxis": {
              "label": "y1Axis",
              "scale": "LINEAR"
            }
          }
        },
        "width": 4,
        "xPos": 8,
        "yPos": 28
      }
    ]
  }
}
